catfacts/__init__.py
catfacts/cli.py
catfacts_cli-0.1.6.dist-info/licenses/LICENSE
catfacts_cli-0.1.6.dist-info/METADATA
catfacts_cli-0.1.6.dist-info/WHEEL
catfacts_cli-0.1.6.dist-info/entry_points.txt
catfacts_cli-0.1.6.dist-info/top_level.txt
catfacts_cli-0.1.6.dist-info/RECORD
